anova_ble/__init__.py
anova_ble/__main__.py
anova_ble/const.py
anova_ble-0.1.6.dist-info/LICENSE
anova_ble-0.1.6.dist-info/METADATA
anova_ble-0.1.6.dist-info/WHEEL
anova_ble-0.1.6.dist-info/RECORD
